vectormorph/__init__.py
vectormorph/vector_morph.py
vectormorph-0.1.3.dist-info/LICENSE
vectormorph-0.1.3.dist-info/METADATA
vectormorph-0.1.3.dist-info/WHEEL
vectormorph-0.1.3.dist-info/entry_points.txt
vectormorph-0.1.3.dist-info/top_level.txt
vectormorph-0.1.3.dist-info/RECORD
